{
  "batchName": "replenish-20260421T001201Z-next33",
  "group": 2,
  "items": [
    {
      "slug": "desierto-sonoro-de-valeria-luiselli",
      "title": "Desierto Sonoro",
      "authorName": "Valeria Luiselli",
      "authorSlug": "valeria-luiselli",
      "type": "ficcion",
      "audience": "todos",
      "genres": [
        "narrativa"
      ],
      "year": null,
      "pages": null,
      "clicks": 1,
      "impressions": 2,
      "priority": 2,
      "current": {
        "summary": "Pendiente de desarrollo editorial.",
        "aboutThisBook": "Ficha en expansión a partir de señal histórica de clicks.",
        "centralConflict": "",
        "themes": [],
        "keyIdeas": [],
        "forWhom": "Pendiente de revisión editorial.",
        "whyItMatters": "Pendiente de revisión editorial.",
        "tone": "",
        "escpilar": false
      },
      "rewritten": {
        "title": "",
        "authorName": "",
        "authorSlug": "",
        "type": "",
        "audience": "",
        "genres": [],
        "year": null,
        "pages": null,
        "summary": "",
        "aboutThisBook": "",
        "forWhom": "",
        "whyItMatters": "",
        "editorialIntro": "",
        "readingLevel": "",
        "whyReadToday": "",
        "studyNotes": [],
        "chapterSummaries": [],
        "analysisSections": [],
        "faqs": [],
        "reviewedAt": "",
        "sources": []
      }
    },
    {
      "slug": "dia-de-perros-de-alicia-gimenez-bartlett",
      "title": "Dia De Perros",
      "authorName": "Alicia Gimenez Bartlett",
      "authorSlug": "alicia-gimenez-bartlett",
      "type": "ficcion",
      "audience": "todos",
      "genres": [
        "narrativa"
      ],
      "year": null,
      "pages": null,
      "clicks": 1,
      "impressions": 2,
      "priority": 6,
      "current": {
        "summary": "Pendiente de desarrollo editorial.",
        "aboutThisBook": "Ficha en expansión a partir de señal histórica de clicks.",
        "centralConflict": "",
        "themes": [],
        "keyIdeas": [],
        "forWhom": "Pendiente de revisión editorial.",
        "whyItMatters": "Pendiente de revisión editorial.",
        "tone": "",
        "escpilar": false
      },
      "rewritten": {
        "title": "",
        "authorName": "",
        "authorSlug": "",
        "type": "",
        "audience": "",
        "genres": [],
        "year": null,
        "pages": null,
        "summary": "",
        "aboutThisBook": "",
        "forWhom": "",
        "whyItMatters": "",
        "editorialIntro": "",
        "readingLevel": "",
        "whyReadToday": "",
        "studyNotes": [],
        "chapterSummaries": [],
        "analysisSections": [],
        "faqs": [],
        "reviewedAt": "",
        "sources": []
      }
    },
    {
      "slug": "dioses-y-mitos-del-antiguo-egipto-de-robert-a-armour",
      "title": "Dioses Y Mitos Del Antiguo Egipto",
      "authorName": "Robert A Armour",
      "authorSlug": "robert-a-armour",
      "type": "ficcion",
      "audience": "todos",
      "genres": [
        "narrativa"
      ],
      "year": null,
      "pages": null,
      "clicks": 1,
      "impressions": 2,
      "priority": 10,
      "current": {
        "summary": "Pendiente de desarrollo editorial.",
        "aboutThisBook": "Ficha en expansión a partir de señal histórica de clicks.",
        "centralConflict": "",
        "themes": [],
        "keyIdeas": [],
        "forWhom": "Pendiente de revisión editorial.",
        "whyItMatters": "Pendiente de revisión editorial.",
        "tone": "",
        "escpilar": false
      },
      "rewritten": {
        "title": "",
        "authorName": "",
        "authorSlug": "",
        "type": "",
        "audience": "",
        "genres": [],
        "year": null,
        "pages": null,
        "summary": "",
        "aboutThisBook": "",
        "forWhom": "",
        "whyItMatters": "",
        "editorialIntro": "",
        "readingLevel": "",
        "whyReadToday": "",
        "studyNotes": [],
        "chapterSummaries": [],
        "analysisSections": [],
        "faqs": [],
        "reviewedAt": "",
        "sources": []
      }
    }
  ]
}