{
  "batchName": "replenish-20260421T185221Z-next65",
  "group": 2,
  "claimedBatchPath": "/Users/clank/.hermes/workspace/webs/131-librosresumidos.net/.work/rewrite-batches/in-progress/replenish-20260421T185221Z-next65.json",
  "items": [
    {
      "slug": "el-sotano-de-natasha-preston",
      "title": "El Sotano",
      "authorName": "Natasha Preston",
      "authorSlug": "natasha-preston",
      "type": "ficcion",
      "audience": "todos",
      "genres": [
        "narrativa"
      ],
      "year": null,
      "pages": null,
      "clicks": 1,
      "impressions": 1,
      "priority": 2,
      "current": {
        "summary": "Pendiente de desarrollo editorial.",
        "aboutThisBook": "Ficha en expansión a partir de señal histórica de clicks.",
        "centralConflict": "",
        "themes": [],
        "keyIdeas": [],
        "forWhom": "Pendiente de revisión editorial.",
        "whyItMatters": "Pendiente de revisión editorial.",
        "tone": "",
        "escpilar": false
      },
      "rewritten": {
        "title": "",
        "authorName": "",
        "authorSlug": "",
        "type": "",
        "audience": "",
        "genres": [],
        "year": null,
        "pages": null,
        "summary": "",
        "aboutThisBook": "",
        "forWhom": "",
        "whyItMatters": "",
        "editorialIntro": "",
        "readingLevel": "",
        "whyReadToday": "",
        "studyNotes": [],
        "chapterSummaries": [],
        "analysisSections": [],
        "faqs": [],
        "reviewedAt": "",
        "sources": []
      }
    },
    {
      "slug": "el-ultimo-tren-a-zurich-de-cesar-vidal",
      "title": "El Ultimo Tren A Zurich",
      "authorName": "Cesar Vidal",
      "authorSlug": "cesar-vidal",
      "type": "ficcion",
      "audience": "todos",
      "genres": [
        "narrativa"
      ],
      "year": null,
      "pages": null,
      "clicks": 1,
      "impressions": 1,
      "priority": 6,
      "current": {
        "summary": "Pendiente de desarrollo editorial.",
        "aboutThisBook": "Ficha en expansión a partir de señal histórica de clicks.",
        "centralConflict": "",
        "themes": [],
        "keyIdeas": [],
        "forWhom": "Pendiente de revisión editorial.",
        "whyItMatters": "Pendiente de revisión editorial.",
        "tone": "",
        "escpilar": false
      },
      "rewritten": {
        "title": "",
        "authorName": "",
        "authorSlug": "",
        "type": "",
        "audience": "",
        "genres": [],
        "year": null,
        "pages": null,
        "summary": "",
        "aboutThisBook": "",
        "forWhom": "",
        "whyItMatters": "",
        "editorialIntro": "",
        "readingLevel": "",
        "whyReadToday": "",
        "studyNotes": [],
        "chapterSummaries": [],
        "analysisSections": [],
        "faqs": [],
        "reviewedAt": "",
        "sources": []
      }
    },
    {
      "slug": "electra-de-benito-perez-galdos",
      "title": "Electra",
      "authorName": "Benito Perez Galdos",
      "authorSlug": "benito-perez-galdos",
      "type": "ficcion",
      "audience": "todos",
      "genres": [
        "narrativa"
      ],
      "year": null,
      "pages": null,
      "clicks": 1,
      "impressions": 1,
      "priority": 10,
      "current": {
        "summary": "Pendiente de desarrollo editorial.",
        "aboutThisBook": "Ficha en expansión a partir de señal histórica de clicks.",
        "centralConflict": "",
        "themes": [],
        "keyIdeas": [],
        "forWhom": "Pendiente de revisión editorial.",
        "whyItMatters": "Pendiente de revisión editorial.",
        "tone": "",
        "escpilar": false
      },
      "rewritten": {
        "title": "",
        "authorName": "",
        "authorSlug": "",
        "type": "",
        "audience": "",
        "genres": [],
        "year": null,
        "pages": null,
        "summary": "",
        "aboutThisBook": "",
        "forWhom": "",
        "whyItMatters": "",
        "editorialIntro": "",
        "readingLevel": "",
        "whyReadToday": "",
        "studyNotes": [],
        "chapterSummaries": [],
        "analysisSections": [],
        "faqs": [],
        "reviewedAt": "",
        "sources": []
      }
    }
  ],
  "required_rewritten_fields": [
    "title",
    "authorName",
    "authorSlug",
    "type",
    "audience",
    "genres",
    "year",
    "pages",
    "summary",
    "aboutThisBook",
    "forWhom",
    "whyItMatters",
    "editorialIntro",
    "readingLevel",
    "whyReadToday",
    "studyNotes",
    "chapterSummaries",
    "analysisSections",
    "faqs",
    "reviewedAt",
    "sources"
  ]
}